zabel/commons/__init__.py
zabel/commons/exceptions.py
zabel/commons/interfaces.py
zabel/commons/kludgeutility.py
zabel/commons/selectors.py
zabel/commons/servers.py
zabel/commons/sessions.py
zabel/commons/utils.py
zabel_commons-1.9.0.dist-info/LICENSE.txt
zabel_commons-1.9.0.dist-info/METADATA
zabel_commons-1.9.0.dist-info/WHEEL
zabel_commons-1.9.0.dist-info/top_level.txt
zabel_commons-1.9.0.dist-info/RECORD
