Metadata-Version: 2.2
Name: zabel-commons
Version: 1.9.0
Summary: The Zabel transverse **commons** library
Home-page: https://github.com/engie-group/zabel
Author: Martin Lafaix
Author-email: martin.lafaix@external.engie.com
License: Eclipse Public License 2.0
Classifier: Development Status :: 5 - Production/Stable
Classifier: Programming Language :: Python :: 3
Classifier: License :: OSI Approved :: Eclipse Public License 2.0 (EPL-2.0)
Classifier: Operating System :: OS Independent
Classifier: Topic :: Utilities
Requires-Python: >= 3.10.0
License-File: LICENSE.txt
Requires-Dist: requests>=2.32
Provides-Extra: bottle
Requires-Dist: bottle>=0.12.25; extra == "bottle"
Provides-Extra: all
Requires-Dist: bottle>=0.12.25; extra == "all"
Dynamic: author
Dynamic: author-email
Dynamic: classifier
Dynamic: description
Dynamic: description-content-type
Dynamic: home-page
Dynamic: license
Dynamic: provides-extra
Dynamic: requires-dist
Dynamic: requires-python
Dynamic: summary
